[
    {
        "commentText": "Ищу работу.\n Водитель. Официант. Знаю столярное дело. Долго работал в лесопромышленной сфере.",
        "commentName": "Сергей",
        "commentDate": "11.05.2019 г.",
        "id": 0
    },
    {
        "commentText": "Вы проживаете в Марселе? Могу предложить Вам работу. Мой телефон 0648418031, Екатерина. Звоните для дополнительной информации.",
        "commentName": "Екатерина",
        "commentDate": "11.10.2019 г.",
        "id": 1
    },
    {
        "commentText": "Привет, Екатерина, я доктор Абдул Халил Абаси, врач общего профиля и педиатр, также занимался косметологией и лфк для позвоночника. Я иммигрант из Афганистана, в РФ учился в СПб, имею разрешение на работу, диплом отправил для подтверждения и экзамена в Париж. Но это долгий процесс. Какая у вас есть интересная работа? Я также могу сделать массаж лица и всего тела на дому. Жду ответа мой тел.0751592929, живу в Мартиге.",
        "commentName": "Абдул халил Абаси",
        "commentDate": "22.10.2020 г.",
        "id": 2
    },
    {
        "commentText": "Ищу работу, любую без знания языка! Благодарю!",
        "commentName": "Anatolii",
        "commentDate": "05.03.2021 г.",
        "id": 3
    },
    {
        "commentText": "Ищу работу горничная, без языка.",
        "commentName": "Зуля",
        "commentDate": "07.01.2019 г.",
        "id": 4
    },
    {
        "commentText": "Ищу работу горничной. Без знания языка.",
        "commentName": "Татьяна",
        "commentDate": "02.06.2019 г.",
        "id": 5
    },
    {
        "commentText": "Здравствуйте, ищу работу в строительстве, мастер внутренних работ и фасадных работ, стаж работы 12 лет.",
        "commentName": "ДЖАМБУЛ",
        "commentDate": "16.02.2021 г.",
        "id": 6
    },
    {
        "commentText": "Ищу работу,ремонт квартир,электрика",
        "commentName": "Виталий",
        "commentDate": "27.06.2019 г.",
        "id": 7
    },
    {
        "commentText": "Ищу работу в Марселе горничной без языка",
        "commentName": "Катя",
        "commentDate": "24.09.2019 г.",
        "id": 8
    },
    {
        "commentText": "Ищу работу в Марселе, парень, ЕС паспорт, язык 4/10. Водитель категории Б и С.",
        "commentName": "Габриел",
        "commentDate": "27.11.2019 г.",
        "id": 9
    },
    {
        "commentText": "Ищу работу в Марселе. Горничная, няня, уборка квартир. Паспорт ЕС. Знаю французский, 1 уровень. Все документы есть. Счёт в банке есть. Опыт работы в отеле есть. 0753114731",
        "commentName": "Наталья",
        "commentDate": "15.01.2020 г.",
        "id": 10
    },
    {
        "commentText": "Ищу работу в Марселе без знания языка. Опытная портная свадебных и вечерних нарядов. Опыт работы 10 лет.",
        "commentName": "Арин",
        "commentDate": "29.01.2020 г.",
        "id": 11
    },
    {
        "commentText": "Я живу в Марселе, ищу работу. Уборка по часам. Я из Украины.",
        "commentName": "Аноним",
        "commentDate": "03.02.2020 г.",
        "id": 12
    },
    {
        "commentText": "Здраствуйте Катерина я из України сейчас в марселе ищу работу",
        "commentName": "Марина",
        "commentDate": "04.02.2020 г.",
        "id": 13
    },
    {
        "commentText": "Живу в марселе, ищу работу без знания языка. Горничная, няня. Я армянка.",
        "commentName": "Лиана",
        "commentDate": "10.02.2020 г.",
        "id": 14
    },
    {
        "commentText": "Здравствуйте,ищу работу в марселе,могу работать няней,есть специальное образование для работы с детьми  и стаж,так же  имеется образование  в сфере визажа,маникюра и наращивания ресниц,знания английского нету,изучаю французский",
        "commentName": "Ольга",
        "commentDate": "24.02.2020 г.",
        "id": 15
    },
    {
        "commentText": "Ищу работу в Марселе, знания итальянского, русского и английского, учу французский.",
        "commentName": "Инна",
        "commentDate": "03.03.2020 г.",
        "id": 16
    },
    {
        "commentText": "Ищу работу в Марселе горничной , я Елена руссская!",
        "commentName": "LENA",
        "commentDate": "24.05.2020 г.",
        "id": 17
    },
    {
        "commentText": "Добрый день. Ищу работу. Любую. Живу в Марселе.",
        "commentName": "Михаил",
        "commentDate": "10.06.2020 г.",
        "id": 18
    },
    {
        "commentText": "добрый день! мы с мужем ищу работу. мы в марселе",
        "commentName": "Юлия",
        "commentDate": "04.07.2020 г.",
        "id": 19
    },
    {
        "commentText": "Ищу работу в Марселе. Без знаний языка.",
        "commentName": "Александра.",
        "commentDate": "25.08.2020 г.",
        "id": 20
    },
    {
        "commentText": "Здравствуйте. Могу предложить вам работу в Марселе.",
        "commentName": "Диана",
        "commentDate": "31.08.2020 г.",
        "id": 21
    },
    {
        "commentText": "Здравствуйте! Я Григорий. Проживаю в Марселе. Владею тремя языками. Скульптор, реставратор, строитель, плотник.",
        "commentName": "Григорий",
        "commentDate": "02.09.2020 г.",
        "id": 22
    },
    {
        "commentText": "Здравствуйте, ищу любую работу. Без знания языка.",
        "commentName": "Люда",
        "commentDate": "23.12.2021 г.",
        "id": 23
    },
    {
        "commentText": "Добрый день, ищу работу в Марселе, все документы в порядке.",
        "commentName": "Roman",
        "commentDate": "25.10.2020 г.",
        "id": 24
    },
    {
        "commentText": "Добрый день, я водитель категории СЕ, работаю в Германии по  рабочей визе. Ищу работу в Марселе водителем СЕ в порту. Паспорт Украины. Имею вид на жительство в Польше до сентября 2023 года. Жена гражданка ЕС.",
        "commentName": "Игорь",
        "commentDate": "02.05.2022 г.",
        "id": 25
    }
]